gcloud_tasks_emulator/__init__.py
gcloud_tasks_emulator/__main__.py
gcloud_tasks_emulator/cloudtasks_pb2_grpc.py
gcloud_tasks_emulator/server.py
gcloud_tasks_emulator/tests.py
gcloud_tasks_emulator-0.6.2.data/scripts/gcloud-tasks-emulator
gcloud_tasks_emulator-0.6.2.data/scripts/gcloud-tasks-emulator.py
gcloud_tasks_emulator-0.6.2.dist-info/LICENCE.md
gcloud_tasks_emulator-0.6.2.dist-info/METADATA
gcloud_tasks_emulator-0.6.2.dist-info/WHEEL
gcloud_tasks_emulator-0.6.2.dist-info/top_level.txt
gcloud_tasks_emulator-0.6.2.dist-info/RECORD
