Metadata-Version: 2.1
Name: gcloud-tasks-emulator
Version: 0.6.2
Summary: A stub emulator for the Google Cloud Tasks API
Home-page: https://gitlab.com/potato-oss/google-cloud/gcloud-tasks-emulator
Author: Potato London Ltd.
Author-email: mail@p.ota.to
License: UNKNOWN
Keywords: Google Cloud Tasks,Google App Engine,GAE,GCP
Platform: UNKNOWN
Classifier: Development Status :: 3 - Alpha
Classifier: Intended Audience :: Developers
Classifier: License :: OSI Approved :: BSD License
Classifier: Operating System :: OS Independent
Classifier: Programming Language :: Python
Requires-Python: >=3.7
License-File: LICENCE.md
Requires-Dist: grpcio >=1.29.0
Requires-Dist: pyyaml >=5.3.1
Requires-Dist: google-cloud-tasks <3,>=2.0.0
Requires-Dist: protobuf <5
